Workbook

Sheet Dashboard
A1: Luxembourg Branch — Regulatory Watch Dashboard
A2: Scope: private banking & mortgage — EU Commission, EP, Council, ESMA, EBA, AMLA, ECB, CSSF, MoF LU
A3: Items tracked: 81 | Last update: 23 July 2026
A5: Total items | B5: =COUNTA('Reg Watch'!A2:A500) | C5: Avg complexity orga | D5: =ROUND(AVERAGE('Reg Watch'!I2:I500),2) | E5: Avg complexity IT | F5: =ROUND(AVERAGE('Reg Watch'!J2:J500),2)
A7: By document status | E7: By high-level topic
A8: Status | B8: Count | C8: Avg complexity (orga) | E8: Topic | F8: Count | G8: Avg complexity (orga)
A9: Draft / Call for evidence | B9: =COUNTIF('Reg Watch'!G2:G500,"Draft / Call for evidence") | C9: =IFERROR(ROUND(AVERAGEIF('Reg Watch'!G2:G500,"Draft / Call for evidence",'Reg Watch'!I2:I500),2),"-") | E9: AML/CFT | F9: =COUNTIF('Reg Watch'!B2:B500,"AML/CFT") | G9: =IFERROR(ROUND(AVERAGEIF('Reg Watch'!B2:B500,"AML/CFT",'Reg Watch'!I2:I500),2),"-")
A10: Public consultation | B10: =COUNTIF('Reg Watch'!G2:G500,"Public consultation") | C10: =IFERROR(ROUND(AVERAGEIF('Reg Watch'!G2:G500,"Public consultation",'Reg Watch'!I2:I500),2),"-") | E10: MiFID / Investment Services | F10: =COUNTIF('Reg Watch'!B2:B500,"MiFID / Investment Services") | G10: =IFERROR(ROUND(AVERAGEIF('Reg Watch'!B2:B500,"MiFID / Investment Services",'Reg Watch'!I2:I500),2),"-")
A11: Trilogue / Political agreement pending | B11: =COUNTIF('Reg Watch'!G2:G500,"Trilogue / Political agreement pending") | C11: =IFERROR(ROUND(AVERAGEIF('Reg Watch'!G2:G500,"Trilogue / Political agreement pending",'Reg Watch'!I2:I500),2),"-") | E11: Payments | F11: =COUNTIF('Reg Watch'!B2:B500,"Payments") | G11: =IFERROR(ROUND(AVERAGEIF('Reg Watch'!B2:B500,"Payments",'Reg Watch'!I2:I500),2),"-")
A12: Political agreement (awaiting OJ) | B12: =COUNTIF('Reg Watch'!G2:G500,"Political agreement (awaiting OJ)") | C12: =IFERROR(ROUND(AVERAGEIF('Reg Watch'!G2:G500,"Political agreement (awaiting OJ)",'Reg Watch'!I2:I500),2),"-") | E12: Cyber & ICT Resilience | F12: =COUNTIF('Reg Watch'!B2:B500,"Cyber & ICT Resilience") | G12: =IFERROR(ROUND(AVERAGEIF('Reg Watch'!B2:B500,"Cyber & ICT Resilience",'Reg Watch'!I2:I500),2),"-")
A13: Adopted (not yet applicable) | B13: =COUNTIF('Reg Watch'!G2:G500,"Adopted (not yet applicable)") | C13: =IFERROR(ROUND(AVERAGEIF('Reg Watch'!G2:G500,"Adopted (not yet applicable)",'Reg Watch'!I2:I500),2),"-") | E13: Outsourcing & Third-Party Risk | F13: =COUNTIF('Reg Watch'!B2:B500,"Outsourcing & Third-Party Risk") | G13: =IFERROR(ROUND(AVERAGEIF('Reg Watch'!B2:B500,"Outsourcing & Third-Party Risk",'Reg Watch'!I2:I500),2),"-")
A14: Partially applicable | B14: =COUNTIF('Reg Watch'!G2:G500,"Partially applicable") | C14: =IFERROR(ROUND(AVERAGEIF('Reg Watch'!G2:G500,"Partially applicable",'Reg Watch'!I2:I500),2),"-") | E14: Prudential (CRR/CRD) | F14: =COUNTIF('Reg Watch'!B2:B500,"Prudential (CRR/CRD)") | G14: =IFERROR(ROUND(AVERAGEIF('Reg Watch'!B2:B500,"Prudential (CRR/CRD)",'Reg Watch'!I2:I500),2),"-")
A15: Applicable / In force | B15: =COUNTIF('Reg Watch'!G2:G500,"Applicable / In force") | C15: =IFERROR(ROUND(AVERAGEIF('Reg Watch'!G2:G500,"Applicable / In force",'Reg Watch'!I2:I500),2),"-") | E15: Retail Credit / Mortgage | F15: =COUNTIF('Reg Watch'!B2:B500,"Retail Credit / Mortgage") | G15: =IFERROR(ROUND(AVERAGEIF('Reg Watch'!B2:B500,"Retail Credit / Mortgage",'Reg Watch'!I2:I500),2),"-")
A16: Level 2 pending | B16: =COUNTIF('Reg Watch'!G2:G500,"Level 2 pending") | C16: =IFERROR(ROUND(AVERAGEIF('Reg Watch'!G2:G500,"Level 2 pending",'Reg Watch'!I2:I500),2),"-") | E16: ESG / Sustainability | F16: =COUNTIF('Reg Watch'!B2:B500,"ESG / Sustainability") | G16: =IFERROR(ROUND(AVERAGEIF('Reg Watch'!B2:B500,"ESG / Sustainability",'Reg Watch'!I2:I500),2),"-")
E17: AI Governance | F17: =COUNTIF('Reg Watch'!B2:B500,"AI Governance") | G17: =IFERROR(ROUND(AVERAGEIF('Reg Watch'!B2:B500,"AI Governance",'Reg Watch'!I2:I500),2),"-")
E18: Post-trade / Market Infra | F18: =COUNTIF('Reg Watch'!B2:B500,"Post-trade / Market Infra") | G18: =IFERROR(ROUND(AVERAGEIF('Reg Watch'!B2:B500,"Post-trade / Market Infra",'Reg Watch'!I2:I500),2),"-")
A19: By issuing institution | E19: Benchmarks | F19: =COUNTIF('Reg Watch'!B2:B500,"Benchmarks") | G19: =IFERROR(ROUND(AVERAGEIF('Reg Watch'!B2:B500,"Benchmarks",'Reg Watch'!I2:I500),2),"-")
A20: Institution | B20: Count | C20: Avg complexity (IT) | E20: Crypto / MiCA | F20: =COUNTIF('Reg Watch'!B2:B500,"Crypto / MiCA") | G20: =IFERROR(ROUND(AVERAGEIF('Reg Watch'!B2:B500,"Crypto / MiCA",'Reg Watch'!I2:I500),2),"-")
A21: EU Commission | B21: =COUNTIF('Reg Watch'!F2:F500,"EU Commission") | C21: =IFERROR(ROUND(AVERAGEIF('Reg Watch'!F2:F500,"EU Commission",'Reg Watch'!J2:J500),2),"-") | E21: Tax / Reporting | F21: =COUNTIF('Reg Watch'!B2:B500,"Tax / Reporting") | G21: =IFERROR(ROUND(AVERAGEIF('Reg Watch'!B2:B500,"Tax / Reporting",'Reg Watch'!I2:I500),2),"-")
A22: European Parliament | B22: =COUNTIF('Reg Watch'!F2:F500,"European Parliament") | C22: =IFERROR(ROUND(AVERAGEIF('Reg Watch'!F2:F500,"European Parliament",'Reg Watch'!J2:J500),2),"-") | E22: Listing / Prospectus | F22: =COUNTIF('Reg Watch'!B2:B500,"Listing / Prospectus") | G22: =IFERROR(ROUND(AVERAGEIF('Reg Watch'!B2:B500,"Listing / Prospectus",'Reg Watch'!I2:I500),2),"-")
A23: EU Council | B23: =COUNTIF('Reg Watch'!F2:F500,"EU Council") | C23: =IFERROR(ROUND(AVERAGEIF('Reg Watch'!F2:F500,"EU Council",'Reg Watch'!J2:J500),2),"-") | E23: Consumer Protection | F23: =COUNTIF('Reg Watch'!B2:B500,"Consumer Protection") | G23: =IFERROR(ROUND(AVERAGEIF('Reg Watch'!B2:B500,"Consumer Protection",'Reg Watch'!I2:I500),2),"-")
A24: EP & Council (co-legislators) | B24: =COUNTIF('Reg Watch'!F2:F500,"EP & Council (co-legislators)") | C24: =IFERROR(ROUND(AVERAGEIF('Reg Watch'!F2:F500,"EP & Council (co-legislators)",'Reg Watch'!J2:J500),2),"-") | E24: Governance & Conduct | F24: =COUNTIF('Reg Watch'!B2:B500,"Governance & Conduct") | G24: =IFERROR(ROUND(AVERAGEIF('Reg Watch'!B2:B500,"Governance & Conduct",'Reg Watch'!I2:I500),2),"-")
A25: ESMA | B25: =COUNTIF('Reg Watch'!F2:F500,"ESMA") | C25: =IFERROR(ROUND(AVERAGEIF('Reg Watch'!F2:F500,"ESMA",'Reg Watch'!J2:J500),2),"-")
A26: EBA | B26: =COUNTIF('Reg Watch'!F2:F500,"EBA") | C26: =IFERROR(ROUND(AVERAGEIF('Reg Watch'!F2:F500,"EBA",'Reg Watch'!J2:J500),2),"-")
A27: EIOPA | B27: =COUNTIF('Reg Watch'!F2:F500,"EIOPA") | C27: =IFERROR(ROUND(AVERAGEIF('Reg Watch'!F2:F500,"EIOPA",'Reg Watch'!J2:J500),2),"-")
A28: AMLA | B28: =COUNTIF('Reg Watch'!F2:F500,"AMLA") | C28: =IFERROR(ROUND(AVERAGEIF('Reg Watch'!F2:F500,"AMLA",'Reg Watch'!J2:J500),2),"-")
A29: ECB | B29: =COUNTIF('Reg Watch'!F2:F500,"ECB") | C29: =IFERROR(ROUND(AVERAGEIF('Reg Watch'!F2:F500,"ECB",'Reg Watch'!J2:J500),2),"-")
A30: CSSF | B30: =COUNTIF('Reg Watch'!F2:F500,"CSSF") | C30: =IFERROR(ROUND(AVERAGEIF('Reg Watch'!F2:F500,"CSSF",'Reg Watch'!J2:J500),2),"-")
A31: Ministry of Finance (LU) | B31: =COUNTIF('Reg Watch'!F2:F500,"Ministry of Finance (LU)") | C31: =IFERROR(ROUND(AVERAGEIF('Reg Watch'!F2:F500,"Ministry of Finance (LU)",'Reg Watch'!J2:J500),2),"-")
A34: Methodology & legend
A35: Complexity 1 = minimal effort (low-impact guidance, monitoring); 2 = focused policy review; 3 = material cross-function project; 4 = multi-stream programme with IT build; 5 = strategic overhaul requiring branch-wide mobilisation, including IT rebuilds.
A36: Status: Draft / Call for evidence = EC non-legislative stage · Public consultation = open to market · Trilogue = co-legislator negotiation · Political agreement (awaiting OJ) = deal struck, legal-linguistic review · Adopted (not yet applicable) = in OJ, awaiting application date · Partially applicable = staggered go-live · Applicable / In force = fully live · Level 2 pending = primary text applicable but RTS/ITS still in flight.
A37: Sources scanned: eur-lex.europa.eu, finance.ec.europa.eu, consilium.europa.eu, europarl.europa.eu, esma.europa.eu, eba.europa.eu, amla.europa.eu, ecb.europa.eu, cssf.lu, legilux.public.lu, mfin.gouvernement.lu.
A38: Refresh cadence recommendation: monthly sweep on CSSF/ESMA/EBA press pages + weekly on EUR-Lex RSS 'Banking & Finance'. Update this file at the end of each sweep and increment the 'Last update' date cell above.

Sheet Reg Watch
A1: item number | B1: high level topic | C1: summary | D1: potential impact | E1: date of publication | F1: issuing institution | G1: status of document | H1: expected date of application | I1: complexity orga | J1: complexity IT | K1: link to document
A2: 1 | B2: MiFID / Investment Services | C2: Retail Investment Strategy (RIS) — omnibus reform of MiFID II, IDD, UCITS, AIFMD, PRIIPs and Solvency II. Introduces value-for-money benchmarks on costs/performance, revised inducement rules with enhanced test & reporting, single disclosure document, reinforced suitability & appropriateness tests, marketing communications register, professional-clients-on-request threshold review, digital-first disclosures. | D2: High impact on private banking: review of discretionary mandate fee grids, rebate/retrocession policy, value-for-money files on model portfolios, revamp of suitability questionnaires and reports, full update of costs & charges ex-ante/ex-post disclosures, revised product governance (target market), staff training and certification. | E2: 13 Dec 2025 (political agreement) | F2: EP & Council (co-legislators) | G2: Political agreement (awaiting OJ) | H2: ≈Q2 2028 (MiFID: 24m from OJ); 18m for PRIIPs amendments | I2: 5 | J2: 5 | K2: https://www.consilium.europa.eu/en/policies/retail-investment-strategy/
A3: 2 | B3: MiFID / Investment Services | C3: ESMA RTS on order execution policies (Art. 27(10) MiFID II as revised) — criteria for establishing, monitoring and assessing effectiveness of execution policies; venue classification & selection; documentation of own-account dealing. | D3: Rewrite of best-execution policy, venue selection methodology, quarterly monitoring of execution quality; IT changes for evidence trail and reporting; relevant for order routing for private banking discretionary and RTO flows. | E3: 18 Apr 2025 (ESMA final report) | F3: ESMA | G3: Adopted (not yet applicable) | H3: ≈Q4 2026 / Q1 2027 (after EC endorsement) | I3: 3 | J3: 3 | K3: https://www.esma.europa.eu/sites/default/files/2025-04/ESMA35-335435667-6253_Final_Report_-_MiFID_II_RTS_on_order_execution_policies.pdf
A4: 3 | B4: MiFID / Investment Services | C4: ESMA consultation on amendments to the MiFID II research regime — clarifying rules on joint payments for execution and research post-Listing Act amendment. | D4: Re-documentation of research procurement, budgeting, allocation to client portfolios; minor-to-moderate policy rewrite. | E4: 2025/2026 (open consultation) | F4: ESMA | G4: Public consultation | H4: Level 2 to follow MiFID review timeline | I4: 2 | J4: 2 | K4: https://www.esma.europa.eu/press-news/esma-news/esma-consults-amendments-mifid-research-regime
A5: 4 | B5: MiFID / Investment Services | C5: MiFID II Quick Fix / Listing Act amendments to Directive 2014/65/EU — tick size, simplified disclosures for bonds, SME growth market adjustments. | D5: Capital markets desk: update of tick-size tables, bond prospectus-light workflow, SME growth market procedures. | E5: 14 Nov 2024 (OJ — Listing Act) | F5: EP & Council (co-legislators) | G5: Partially applicable | H5: Various — most provisions 2025/2026 | I5: 2 | J5: 2 | K5: https://eur-lex.europa.eu/eli/dir/2024/2811/oj
A6: 5 | B6: Listing / Prospectus | C6: Listing Act - Wave 2 Prospectus Regulation amendments: simplified secondary issuance prospectus, EU Follow-on Prospectus, EU Growth Issuance Document, URD streamlining, standardised sequence & format of base prospectuses & final terms. Level 1 amendments became applicable on 5 June 2026; the related Prospectus Delegated Regulation amendments (Delegated Act adopted 7 May 2026) have delayed applicability, with ESMA recommending interim use of the adopted Delegated Act provisions. | D6: Treasury / EMTN programmes and structured-product issuance: prospectus template update, annexes re-sequencing, base-prospectus workflow review; limited direct impact on pure private banking advisory. | E6: 14 Nov 2024 (OJ) | F6: EP & Council (co-legislators) | G6: Applicable / In force | H6: Applied from 5 June 2026 (Level 1) | I6: 3 | J6: 2 | K6: https://eur-lex.europa.eu/eli/reg/2024/2809/oj
A7: 6 | B7: Listing / Prospectus | C7: ESMA public statement supporting smooth implementation of the Listing Act prospectus changes — transition treatment of pending prospectuses, approach to ESMA32 technical instructions pending Level 2. | D7: Operational guidance note for the capital markets team; update internal 'prospectus Q&A' memorandum. | E7: 18 Feb 2026 | F7: ESMA | G7: Applicable / In force | H7: Applies from 18 Feb 2026 | I7: 2 | J7: 1 | K7: https://www.esma.europa.eu/press-news/esma-news/esma-publishes-statement-supporting-smooth-implementation-listing-act
A8: 7 | B8: Listing / Prospectus | C8: EC Delegated Act amending Commission Delegated Regulation 2019/980 — adopted on 7 May 2026. Revises prospectus format and sequencing of information items and introduces a new annex with disclosure requirements for non-equity securities marketed as ESG-related. Now subject to a 3-month Parliament/Council scrutiny period before publication in the OJ; will enter into force 3 days after OJ. | D8: Update of drafting templates and XBRL tagging workflow for prospectuses. | E8: 7 May 2026 | F8: EU Commission | G8: Adopted (not yet applicable) | H8: OJ Q3 2026; entry into force 3 days after OJ | I8: 2 | J8: 2 | K8: https://finance.ec.europa.eu/regulation-and-supervision/financial-services-legislation/implementing-and-delegated-acts/prospectus-regulation_en
A9: 8 | B9: AML/CFT | C9: AML Regulation (Reg (EU) 2024/1624 — 'AMLR') — single directly-applicable rulebook: CDD, EDD/SDD, beneficial ownership, PEPs, reliance on third parties, transfer of funds rules, record-keeping, internal control requirements. | D9: Full rewrite of AML policy, KYC onboarding flows and ongoing-due-diligence triggers; enhanced source-of-wealth/source-of-funds evidencing for private banking clients; screening/BO register integration; staff training; branch must align with parent group AML policy but apply LU specifics. | E9: 19 Jun 2024 (OJ) | F9: EP & Council (co-legislators) | G9: Adopted (not yet applicable) | H9: 10 July 2027 | I9: 5 | J9: 4 | K9: https://eur-lex.europa.eu/eli/reg/2024/1624/oj
A10: 9 | B10: AML/CFT | C10: 6th AML Directive (Dir (EU) 2024/1640 — 'AMLD6') — Member-State obligations on FIU, BO register access, national risk assessment, cross-border cooperation, sanctions, statistics. | D10: Monitor LU transposition (amendments to Law of 12 Nov 2004); update access procedures to BO register, FIU reporting flows, fit-and-proper procedures. | E10: 19 Jun 2024 (OJ) | F10: EP & Council (co-legislators) | G10: Adopted (not yet applicable) | H10: 10 July 2027 (general transposition) | I10: 3 | J10: 2 | K10: https://eur-lex.europa.eu/eli/dir/2024/1640/oj
A11: 10 | B11: AML/CFT | C11: AMLA Regulation (Reg (EU) 2024/1620) — establishing the EU AML Authority in Frankfurt; direct supervision of ~40 selected obliged entities and indirect supervision of the rest via NCAs; power to issue RTS, guidelines, Q&As. | D11: Prepare for AMLA selection criteria (cross-border presence, risk profile); strengthen governance & data availability for indirect supervision via CSSF. | E11: 19 Jun 2024 (OJ) | F11: EP & Council (co-legislators) | G11: Partially applicable | H11: Direct supervision: 2028 | I11: 3 | J11: 2 | K11: https://eur-lex.europa.eu/eli/reg/2024/1620/oj
A12: 11 | B12: AML/CFT | C12: AMLA draft RTS on Customer Due Diligence (Art. 28(1) AMLR). Written-submission window closed 8 May 2026 after first public hearing on 24 March 2026 (~1,600 stakeholders). AMLA will finalise the draft and submit to the Commission by 10 July 2026 for endorsement; applicable alongside AMLR on 10 July 2027. | D12: Highest AML priority of 2026: full CDD framework re-write, remote onboarding gap analysis, documentation uplift, risk-scoring methodology recalibration. | E12: 9 Feb 2026 (consultation launched) | F12: AMLA | G12: Level 2 pending | H12: Consultation closed 8 May 2026; final RTS submitted to European Commission 10 Jul 2026, pending Commission adoption; applicable 10 Jul 2027 | I12: 5 | J12: 4 | K12: https://www.amla.europa.eu/policy/regulatory-instruments_en
A13: 12 | B13: AML/CFT | C13: AMLA draft RTS on pecuniary sanctions & administrative measures — methodology for calibration of AML sanctions by NCAs. | D13: Policy impact limited for 1st line; compliance/legal need to update sanctions-exposure assessments. | E13: 9 Feb 2026 (consultation) | F13: AMLA | G13: Level 2 pending | H13: Consultation closed 9 Mar 2026; final RTS submitted to European Commission 10 Jul 2026, pending Commission adoption | I13: 2 | J13: 1 | K13: https://www.amla.europa.eu/policy/regulatory-instruments_en
... A82: 81 | B82: AML/CFT | C82: AMLA finalised standards (21 July 2026) governing its cooperation with national financial supervisors for the selection and direct supervision of the most significant cross-border financial institutions in the EU. The standards cover selection criteria, the handoff of supervisory responsibility between national and EU level, and joint working arrangements ahead of AMLA assuming direct supervision of selected institutions from 2028. | D82: Sets the operating model for how a cross-border branch could transition from CSSF-led to AMLA-led (or joint) AML/CFT supervision if selected as a directly-supervised entity from 2028; governance and liaison arrangements with Group compliance should be reviewed against the new cooperation standards ahead of the 2027 selection round. | E82: 21 July 2026 | F82: AMLA | G82: Applicable / In force | H82: Direct supervision of selected entities begins 2028 | I82: 3 | J82: 1 | K82: https://www.amla.europa.eu/amla-takes-next-step-toward-2027-selection-entities-direct-supervision_en

Sheet _lists
A1: TOPICS | B1: INSTITUTIONS | C1: STATUSES
A2: AML/CFT | B2: EU Commission | C2: Draft / Call for evidence
A3: MiFID / Investment Services | B3: European Parliament | C3: Public consultation
A4: Payments | B4: EU Council | C4: Trilogue / Political agreement pending
A5: Cyber & ICT Resilience | B5: EP & Council (co-legislators) | C5: Political agreement (awaiting OJ)
A6: Outsourcing & Third-Party Risk | B6: ESMA | C6: Adopted (not yet applicable)
A7: Retail Credit / Mortgage | B7: EBA | C7: Partially applicable
A8: ESG / Sustainability | B8: EIOPA | C8: Applicable / In force
A9: AI Governance | B9: AMLA | C9: Level 2 pending
A10: Post-trade / Market Infra | B10: ECB
A11: Crypto / MiCA | B11: CSSF
A12: Tax / Reporting | B12: Ministry of Finance (LU)
A13: Consumer Protection
A14: Governance & Conduct
A15: Digital Currencies / CBDC
